<?xml version="1.0" encoding="UTF-8"?>
<AssetDeclaration xmlns="uri:ea.com:eala:asset" xmlns:xsi="http://www.w3.org/2001/XMLSchema-instance">
  <Tags></Tags>
  <Includes>
  </Includes>

  <SkirmishOpeningMove
    id="SteelTalons_EASY"
    Side="SteelTalons"> <!--Power: +10-->
    <Order Build="SteelTalonsCrane" /> <!--Time: 15 Power: -10-->
	<Order Build="SteelTalonsPowerPlant" /> <!--Time: 7 Power: +20-->
    <Order Build="SteelTalonsBarracks" /> <!--Time: 5 Power: -5-->
    <Order Build="SteelTalonsBarracks" /> <!--Time: 5 Power: -5-->
    <Order Build="SteelTalonsPowerPlant" /> <!--Time: 7 Power: +20-->
    <Order Build="SteelTalonsRefinery" /> <!--Time: 30 Power: -15-->
    <Order Build="SteelTalonsWarfactory" /> <!--Time: 20 Power: -7-->
    <Order Build="SteelTalonsPowerPlant" /> <!--Time: 7 Power: +20-->

    <Order Build="SteelTalonsRifleSoldierSquad" />
    <Order Build="SteelTalonsRifleSoldierSquad" />
    <Order Build="SteelTalonsRifleSoldierSquad" />
    
    <Order Build="SteelTalonsRifleSoldierSquad" />
    <Order Build="SteelTalonsRifleSoldierSquad" />
    <Order Build="SteelTalonsRifleSoldierSquad" />

    <Order Build="SteelTalonsRifleSoldierSquad" />
    <Order Build="SteelTalonsRifleSoldierSquad" />
    <Order Build="SteelTalonsRifleSoldierSquad" />

    <Order Build="SteelTalonsRifleSoldierSquad" />
    <Order Build="SteelTalonsRifleSoldierSquad" />
    <Order Build="SteelTalonsRifleSoldierSquad" />
    
    <Order Time="180s" />
  </SkirmishOpeningMove>

	<SkirmishOpeningMove
    id="SteelTalonsStandard"
    Side="SteelTalons"> <!--Power: +10-->
		<Order Build="SteelTalonsPowerPlant" /> <!--Time: 7 Power: +20-->
		<Order Build="SteelTalonsBarracks" /> <!--Time: 5 Power: -5-->
		<Order Build="SteelTalonsRifleSoldierSquad" />
		<Order Build="SteelTalonsRifleSoldierSquad" />
		<Order Build="SteelTalonsRefinery" /> <!--Time: 30 Power: -15-->
		<Order Build="SteelTalonsPowerPlant" /> <!--Time: 7 Power: +20-->
		<Order Build="SteelTalonsRefinery" /> <!--Time: 30 Power: -15-->
		<Order Build="SteelTalonsWarfactory" /> <!--Time: 20 Power: -7-->
		<Order Time="99s" Account="PRODUCTION" Deposit="1000" />
		<Order Build="SteelTalonsPowerPlant" /> <!--Time: 7 Power: +20-->
		<Order Build="SteelTalonsRefinery" /> <!--Time: 30 Power: -15-->
		<Order Build="SteelTalonsPowerPlant" /> <!--Time: 7 Power: +20-->
		<Order Build="SteelTalonsRefinery" /> <!--Time: 30 Power: -15-->
		<Order Time="173s" />
	</SkirmishOpeningMove>

	<SkirmishOpeningMove
    id="SteelTalonsStandard2"
    Side="SteelTalons"> <!--Power: +10-->
		<Order Build="SteelTalonsPowerPlant" /> <!--Time: 7 Power: +20-->
		<Order Build="SteelTalonsRefinery" /> <!--Time: 30 Power: -15-->
		<Order Build="SteelTalonsWarfactory" /> <!--Time: 20 Power: -7-->
		<Order Build="SteelTalonsPowerPlant" /> <!--Time: 7 Power: +20-->
		<Order Time="64s" Account="PRODUCTION" Deposit="4500" />
		<Order Build="SteelTalonsRefinery" /> <!--Time: 30 Power: -15-->
		<Order Build="SteelTalonsPowerPlant" /> <!--Time: 7 Power: +20-->
		<Order Build="SteelTalonsRefinery" /> <!--Time: 30 Power: -15-->
		<Order Build="SteelTalonsBarracks" /> <!--Time: 5 Power: -5-->
		<Order Build="SteelTalonsPowerPlant" /> <!--Time: 7 Power: +20-->
		<Order Build="SteelTalonsRefinery" /> <!--Time: 30 Power: -15-->
		<Order Time="173s" />
	</SkirmishOpeningMove>

	<SkirmishOpeningMove
    id="SteelTalonsStandardCrane"
    Side="SteelTalons"> <!--Power: +10-->
		<Order Build="SteelTalonsPowerPlant" /> <!--Time: 7 Power: +20-->
		<Order Build="SteelTalonsBarracks" /> <!--Time: 5 Power: -5-->
		<Order Build="SteelTalonsRefinery" /> <!--Time: 30 Power: -15-->
		<Order Build="SteelTalonsCrane" /> <!--Time: 15 Power: -10-->
		<Order Build="SteelTalonsPowerPlant" /> <!--Time: 7 Power: +20-->
		<Order Build="SteelTalonsRefinery" /> <!--Time: 30 Power: -15-->
		<Order Build="SteelTalonsPowerPlant" /> <!--Time: 7 Power: +20-->
		<Order Build="SteelTalonsRefinery" /> <!--Time: 30 Power: -15-->
		<Order Build="SteelTalonsWarfactory" /> <!--Time: 20 Power: -7-->
		<!--Order Time="151s" Account="PRODUCTION" Deposit="2000" /-->
		<Order Build="SteelTalonsPowerPlant" /> <!--Time: 7 Power: +20-->
		<Order Build="SteelTalonsRefinery" /> <!--Time: 30 Power: -15-->
		<Order Time="188s" />
	</SkirmishOpeningMove>

	<SkirmishOpeningMove
    id="SteelTalonsBrutalCrane"
    Side="SteelTalons"> <!--Power: +10-->
		<Order Build="SteelTalonsPowerPlant" /> <!--Time: 7 Power: +20-->
		<Order Build="SteelTalonsBarracks" /> <!--Time: 5 Power: -5-->
		<Order Build="SteelTalonsRefinery" /> <!--Time: 30 Power: -15-->
		<Order Build="SteelTalonsCrane" /> <!--Time: 15 Power: -10-->
		<Order Build="SteelTalonsPowerPlant" /> <!--Time: 7 Power: +20-->
		<Order Build="SteelTalonsRefinery" /> <!--Time: 30 Power: -15-->
		<Order Build="SteelTalonsPowerPlant" /> <!--Time: 7 Power: +20-->
		<Order Build="SteelTalonsWarfactory" /> <!--Time: 20 Power: -7-->
		<Order Time="121s" Account="PRODUCTION" Deposit="999999" />
		<Order Build="SteelTalonsRefinery" /> <!--Time: 30 Power: -15-->
		<Order Build="SteelTalonsPowerPlant" /> <!--Time: 7 Power: +20-->
		<Order Build="SteelTalonsWarfactory" /> <!--Time: 20 Power: -7-->
		<Order Build="SteelTalonsRefinery" /> <!--Time: 30 Power: -15-->
		<Order Build="SteelTalonsPowerPlant" /> <!--Time: 7 Power: +20-->
		<Order Build="SteelTalonsBarracks" /> <!--Time: 5 Power: -5-->
		<Order Build="SteelTalonsRefinery" /> <!--Time: 30 Power: -15-->
		<Order Time="250s" />
	</SkirmishOpeningMove>

</AssetDeclaration>