<?xml version="1.0" encoding="utf-8"?>
<AssetDeclaration xmlns="uri:ea.com:eala:asset" xmlns:xsi="http://www.w3.org/2001/XMLSchema-instance">
	<Tags></Tags>
	<Includes>
		<Include
			type="all"
			source="ART:DCBComme01.w3x" />
	</Includes>
	<GameObject
		id="DCBComme01"
		SelectPortrait="SABarracks_L"
		ButtonImage="SABarracks"
		Side="Civilian"
		TransportSlotCount="1"
		BuildCost="1"
		BuildTime="10.0"
		CommandSet="EmptyCommandSet"
		KindOf="STRUCTURE IMMOBILE CAN_CAST_REFLECTIONS"
		RadarPriority="STRUCTURE"
		EditorName="DCBComme01"
    EditorSorting="STRUCTURE"
		Browser="REGION Washington_DC_DC STRUCTURE">
		<DisplayName>Washington Commerce Building 01</DisplayName>
		<ArmorSet
			Armor="StructureArmor" />
		<Draws>
			<ScriptedModelDraw
				id="ModuleTag_Draw"
				OkToChangeModelColor="true">
				<ModelConditionState
					ParseCondStateType="PARSE_DEFAULT">
					<Model
						Name="DCBComme01" />
				</ModelConditionState>
			</ScriptedModelDraw>
		</Draws>
		<Behaviors></Behaviors>
		<Body>
			<ActiveBody
				id="ModuleTag_Body"
				MaxHealth="6000.0"
				InitialHealth="6000.0" />
		</Body>
		<Geometry
			IsSmall="false">
			<Shape
				Type="BOX"
				MajorRadius="166.737"
				MinorRadius="94.9911"
				Height="90.3807"
				ContactPointGeneration="STRUCTURE">
				<Offset
					x="-17.218"
					y="-397.918"
					z="0.0" />
			</Shape>
			<Shape
				Type="BOX"
				MajorRadius="166.737"
				MinorRadius="94.9911"
				Height="90.3807"
				ContactPointGeneration="STRUCTURE">
				<Offset
					x="-17.218"
					y="394.144"
					z="0.0" />
			</Shape>
			<Shape
				Type="BOX"
				MajorRadius="141.415"
				MinorRadius="299.191"
				Height="96.6139"
				ContactPointGeneration="STRUCTURE">
				<Offset
					x="-44.7187"
					y="-1.17151"
					z="0.0" />
			</Shape>
			<Shape
				Type="BOX"
				MajorRadius="22.0375"
				MinorRadius="176.851"
				Height="94.7614"
				ContactPointGeneration="STRUCTURE">
				<Offset
					x="90.1968"
					y="19.0225"
					z="0.0" />
			</Shape>
		</Geometry>
		<ShadowInfo
			Type="VOLUME" />
		<VisionInfo
			VisionRange="100"
			ShroudClearingRange="200" />
	</GameObject>
</AssetDeclaration>