<?xml version="1.0" encoding="utf-8"?>
<AssetDeclaration xmlns="uri:ea.com:eala:asset" xmlns:xsi="http://www.w3.org/2001/XMLSchema-instance" xmlns:xi="http://www.w3.org/2001/XInclude">
	<Tags></Tags>
	<Includes>
		<Include
			type="all"
			source="ART:EEBHse01.w3x" />
		<Include
			type="all"
			source="ART:EEBHse01_D1.w3x" />
		<Include
			type="all"
			source="ART:EEBHse01_D2.w3x" />
		<Include
			type="all"
			source="ART:EEBHse01_D3.w3x" />
		<Include
			type="instance"
			source="DATA:BaseObjects/BaseCivilianStructure.xml" />
	</Includes>
	<GameObject
		id="Eastern_Europe_House_01"
		inheritFrom="BaseCivilianStructure"
		EditorName="Eastern_Europe_House_01"
    		EditorSorting="STRUCTURE"
		Browser="REGION Eastern_Europe_EE STRUCTURE">
		<Draws>
			<ScriptedModelDraw
				id="ModuleTag_Draw"
				OkToChangeModelColor="false"
				AffectedByStealth="false"
				ExtraPublicBone="BONEGARRISON01 BONEGARRISON02 BONEGARRISON03 BONEGARRISON04 BONEGARRISON05 BONEGARRISON06 BONEGARRISON07 BONEGARRISON08 BONEGARRISON09 BONEGARRISON10 BONEGARRISON11 BONEGARRISON12">
				<ModelConditionState
					ParseCondStateType="PARSE_DEFAULT">
					<Model
						Name="EEBHse01" />
				</ModelConditionState>
				<ModelConditionState
					ParseCondStateType="PARSE_NORMAL"
					ConditionsYes="RUBBLE">
					<Model
						Name="EEBHse01_D3" />
				</ModelConditionState>
				<ModelConditionState
					ParseCondStateType="PARSE_NORMAL"
					ConditionsYes="REALLYDAMAGED">
					<Model
						Name="EEBHse01_D2" />
				</ModelConditionState>
				<ModelConditionState
					ParseCondStateType="PARSE_NORMAL"
					ConditionsYes="DAMAGED">
					<Model
						Name="EEBHse01_D1" />
				</ModelConditionState>
				<AnimationState
					ParseCondStateType="PARSE_DEFAULT">
					<!-- no anim -->
				</AnimationState>
				<AnimationState
					ParseCondStateType="PARSE_NORMAL"
					ConditionsYes="RUBBLE"
					StateName="STATE_Rubble"
					Flags="START_FRAME_LAST">
					<Animation
						AnimationName="EEBHse01_D3"
						AnimationMode="MANUAL" />
					<Script>
            Prev = CurDrawablePrevAnimationState();
            if Prev ~= null and Prev ~= "STATE_Rubble" and Prev ~= "TRANS_IntoRubble" then
            CurDrawableSetTransitionAnimState("TRANS_IntoRubble")
            end
          </Script>
				</AnimationState>
				<AnimationState
					ParseCondStateType="PARSE_NORMAL"
					ConditionsYes="REALLYDAMAGED"
					StateName="STATE_ReallyDamaged"
					Flags="START_FRAME_LAST">
					<Animation
						AnimationName="EEBHse01_D2"
						AnimationMode="MANUAL" />
					<Script>
            Prev = CurDrawablePrevAnimationState();
            if Prev ~= null and Prev ~= "STATE_ReallyDamaged" and Prev ~= "TRANS_IntoReallyDamaged" then
            CurDrawableSetTransitionAnimState("TRANS_IntoReallyDamaged")
            end
          </Script>
				</AnimationState>
				<AnimationState
					ParseCondStateType="PARSE_NORMAL"
					ConditionsYes="DAMAGED"
					StateName="STATE_Damaged"
					Flags="START_FRAME_LAST">
					<Animation
						AnimationName="EEBHse01_D1"
						AnimationMode="MANUAL" />
					<Script>
            Prev = CurDrawablePrevAnimationState();
            if Prev ~= null and Prev ~= "STATE_Damaged" and Prev ~= "TRANS_IntoDamaged" then
            CurDrawableSetTransitionAnimState("TRANS_IntoDamaged")
            end
          </Script>
				</AnimationState>
				<AnimationState
					ParseCondStateType="PARSE_TRANSITION"
					StateName="TRANS_IntoDamaged">
					<Animation
						AnimationName="EEBHse01_D1"
						AnimationMode="ONCE"
						AnimationBlendTime="0" />
				</AnimationState>
				<AnimationState
					ParseCondStateType="PARSE_TRANSITION"
					StateName="TRANS_IntoReallyDamaged">
					<Animation
						AnimationName="EEBHse01_D2"
						AnimationMode="ONCE"
						AnimationBlendTime="0" />
				</AnimationState>
				<AnimationState
					ParseCondStateType="PARSE_TRANSITION"
					StateName="TRANS_IntoRubble">
					<Animation
						AnimationName="EEBHse01_D3"
						AnimationMode="ONCE"
						AnimationBlendTime="0" />
					<ParticleSysBone
						BoneName="NONE"
						FXParticleSystemTemplate="CivBuildingDust"
						FollowBone="false" />
					<ParticleSysBone
						BoneName="NONE"
						FXParticleSystemTemplate="CivBuildingDust02"
						FollowBone="false" />
				</AnimationState>
			</ScriptedModelDraw>
			<xi:include
				href="DATA:Includes/GarrisonFlagArmorDraw.xml"
				xpointer="xmlns(n=uri:ea.com:eala:asset) xpointer(/n:CommonArmorDraws/child::*)" />
		</Draws>
		<Behaviors></Behaviors>
		<Body>
			<ActiveBody
				id="ModuleTag_Body"
				MaxHealth="=$CIV_HEALTH_SMALL" />
		</Body>
		<Geometry
			IsSmall="false">
			<Shape
				Type="BOX"
				MajorRadius="14.5782"
				MinorRadius="21.3066"
				Height="23.8553"
				ContactPointGeneration="STRUCTURE">
				<Offset
					x="-13.1732"
					y="-44.2358"
					z="0.0" />
			</Shape>
			<Shape
				Type="BOX"
				MajorRadius="38.4335"
				MinorRadius="32.3168"
				Height="47.5067"
				ContactPointGeneration="STRUCTURE">
				<Offset
					x="0.283607"
					y="-0.195267"
					z="0.0" />
			</Shape>
		</Geometry>
	</GameObject>
</AssetDeclaration>