<?xml version="1.0" encoding="UTF-8"?>
<AssetDeclaration xmlns="uri:ea.com:eala:asset" xmlns:xsi="http://www.w3.org/2001/XMLSchema-instance">
  <Tags></Tags>
  <Includes>

    <Include type="all" source="DATA:civilian/props/CIMonorrail.xml" />
    <Include type="all" source="DATA:civilian/props/CIMonoTrack.xml" />
    <Include type="all" source="DATA:civilian/props/PM_Limo01.xml" />
    <Include type="all" source="DATA:civilian/props/PM_Hatchback01.xml" />
    <Include type="all" source="DATA:civilian/props/PM_Hatchback02.xml" />
    <Include type="all" source="DATA:civilian/props/PM_Hatchback03.xml" />
    <Include type="all" source="DATA:civilian/props/PM_Hatchback04.xml" />
    <Include type="all" source="DATA:civilian/props/PM_3Wheel01.xml" />
    <Include type="all" source="DATA:civilian/props/PM_3Wheel02.xml" />
    <Include type="all" source="DATA:civilian/props/PM_3Wheel03.xml" />
    <Include type="all" source="DATA:civilian/props/PM_3Wheel04.xml" />
    <Include type="all" source="DATA:civilian/props/CBIrrigation01.xml" />
    <Include type="all" source="DATA:civilian/props/CBIrrigation02.xml" />
    <Include type="all" source="DATA:civilian/props/CBIrrigation03.xml" />
    <Include type="all" source="DATA:civilian/props/CBIrrigation04.xml" />
    <Include type="all" source="DATA:civilian/props/CBIrrigation05.xml" />
    <Include type="all" source="DATA:civilian/props/CBIrrigation06.xml" />
    <Include type="all" source="DATA:civilian/props/CBIrrigation07.xml" />
    <Include type="all" source="DATA:civilian/props/CBGreenhouse01.xml" />
    <Include type="all" source="DATA:civilian/props/CBWaterTank01.xml" />
    <Include type="all" source="DATA:Civilian/Homeland/CIFreeway.xml" />
    <Include type="all" source="DATA:Civilian/Homeland/CIFreeway02.xml" />
    <Include type="all" source="DATA:Civilian/Homeland/CIFreeway03.xml" />
    <Include type="all" source="DATA:Civilian/Homeland/CITollbooth.xml" />
    <Include type="all" source="DATA:Civilian/Homeland/CICone02.xml" />
    <Include type="all" source="DATA:Civilian/Homeland/FarmSilo.xml" />
    <Include type="all" source="DATA:Civilian/Homeland/CityGarbageBin.xml" />
    <Include type="all" source="DATA:Civilian/Homeland/CIPowerTower.xml" />
    <Include type="all" source="DATA:Civilian/Homeland/CityBuilding05.xml" />
    <Include type="all" source="DATA:Civilian/Homeland/CityGarbageCan.xml" />
    <Include type="all" source="DATA:Civilian/Homeland/CityNewsStand.xml" />
    <Include type="all" source="DATA:Civilian/Homeland/CitySidewalk.xml" />
    <Include type="all" source="DATA:Civilian/Homeland/FarmBarn.xml" />
    <Include type="all" source="DATA:Civilian/Homeland/FarmBarnB.xml" />
    <Include type="all" source="DATA:Civilian/Homeland/FarmCrop_01.xml" />
    <Include type="all" source="DATA:Civilian/Homeland/FarmFence.xml" />
    <Include type="all" source="DATA:Civilian/Homeland/FarmTractor.xml" />
    <Include type="all" source="DATA:Civilian/Homeland/FarmWindmill.xml" />
    <Include type="all" source="DATA:Civilian/Homeland/HATree01.xml" />
    <Include type="all" source="DATA:Civilian/Homeland/ParkBench.xml" />
    <Include type="all" source="DATA:Civilian/Homeland/ParkPaths.xml" />
    <Include type="all" source="DATA:Civilian/Homeland/ParkPicnic.xml" />
    <Include type="all" source="DATA:Civilian/Homeland/ParkPlant02.xml" />
    <Include type="all" source="DATA:Civilian/Homeland/ParkPlant03.xml" />
    <Include type="all" source="DATA:Civilian/Homeland/ParkPlygrnd01.xml" />
    <Include type="all" source="DATA:Civilian/Homeland/ParkPlygrnd02.xml" />
    <Include type="all" source="DATA:Civilian/Homeland/ParkStatue.xml" />
    <Include type="all" source="DATA:Civilian/Homeland/ParkTable.xml" />
    <Include type="all" source="DATA:Civilian/Homeland/PMAuto01.xml" />
    <Include type="all" source="DATA:Civilian/Homeland/PMAuto02.xml" />
    <Include type="all" source="DATA:Civilian/Homeland/PMAuto03.xml" />
    <Include type="all" source="DATA:Civilian/Homeland/PMAuto04.xml" />
    <Include type="all" source="DATA:Civilian/Homeland/TallTree.xml" />
    <Include type="all" source="DATA:Civilian/Homeland/CityLight01.xml" />
    <Include type="all" source="DATA:Civilian/Homeland/CityLight02.xml" />
    <Include type="all" source="DATA:Civilian/Homeland/CityLight03.xml" />
    <Include type="all" source="DATA:Civilian/Homeland/CitySign02.xml" />
    <Include type="all" source="DATA:Civilian/Homeland/CitySign03.xml" />
    <Include type="all" source="DATA:Civilian/Homeland/CitySign04.xml" />
    <Include type="all" source="DATA:Civilian/Homeland/CitySign05.xml" />
    <Include type="all" source="DATA:Civilian/Homeland/CitySign06.xml" />
    <Include type="all" source="DATA:Civilian/Homeland/CityTree01.xml" />
    <Include type="all" source="DATA:Civilian/Homeland/CityTree02.xml" />
    <Include type="all" source="DATA:Civilian/Homeland/CityTree02b.xml" />
    <Include type="all" source="DATA:Civilian/Homeland/CityTree02c.xml" />
    <Include type="all" source="DATA:Civilian/Homeland/HARoad01.xml" />
    <Include type="all" source="DATA:Civilian/Homeland/city_buildings2.xml" />
    <Include type="all" source="DATA:Civilian/Homeland/citybuildings2b.xml" />
    <Include type="all" source="DATA:Civilian/Homeland/PMWreckedAuto01.xml" />
    <Include type="all" source="DATA:Civilian/Homeland/PMWreckedAuto02.xml" />
    <Include type="all" source="DATA:Civilian/Homeland/PMWreckedAuto03.xml" />
    <Include type="all" source="DATA:Civilian/Homeland/PMWreckedAuto04.xml" />
    <Include type="all" source="DATA:Civilian/Homeland/PMWreckedAuto05.xml" />
    <Include type="all" source="DATA:Civilian/Homeland/PMWreckedAuto06.xml" />
    <Include type="all" source="DATA:Civilian/Homeland/PMWreckedAuto07.xml" />
    <Include type="all" source="DATA:Civilian/Homeland/CityBuilding04.xml" />
    <Include type="all" source="DATA:Civilian/Homeland/CIChainlink.xml" />
    <Include type="all" source="DATA:Civilian/Homeland/CIChaingate.xml" />
    <Include type="all" source="DATA:Civilian/Homeland/ParkPool.xml" />
    <Include type="all" source="DATA:Civilian/Homeland/citybuilding02.xml" />
    <Include type="all" source="DATA:Civilian/Homeland/hacorn01.xml" />
    
  </Includes>

</AssetDeclaration>
