<?xml version="1.0" encoding="UTF-8"?>
<AssetDeclaration xmlns="uri:ea.com:eala:asset" xmlns:xsi="http://www.w3.org/2001/XMLSchema-instance">
  <Tags></Tags>
  <Includes>
  </Includes>

  <SkirmishOpeningMove
   id="Traveler59StormriderRush"
   Side="Traveler59">

    <Order Build="Traveler59TiberiumTower" />
    <Order Build="Traveler59PowerProjector" />
    <Order Build="Traveler59TiberiumTower" />
    <Order Build="Traveler59TiberiumTower" />
    <Order Build="Traveler59PowerProjector" />
    <Order Build="Traveler59ControlCenter" />
    <Order Build="Traveler59WarpBeacon" />
    <Order Build="Traveler59WarpBeacon" />

    <Order Build="Traveler59Stormrider" />
    <Order Build="Traveler59Stormrider" />
    <Order Build="Traveler59Stormrider" />
    <Order Build="Traveler59Stormrider" />
    <Order Build="Traveler59Stormrider" />
    <Order Build="Traveler59Stormrider" />
    <Order Build="Traveler59Stormrider" />
    <Order Build="Traveler59Stormrider" />
    <Order Time="175s" />
  </SkirmishOpeningMove>

  <SkirmishOpeningMove
   id="Traveler59RavagerRush"
   Side="Traveler59">

    <Order Build="Traveler59TiberiumTower" />
    <Order Build="Traveler59PowerProjector" />
    <Order Build="Traveler59TiberiumTower" />
    <Order Build="Traveler59TiberiumTower" />
    <Order Build="Traveler59PowerProjector" />
    <Order Build="Traveler59ControlCenter" />
    <Order Build="Traveler59Portal" />
    <Order Build="Traveler59Portal" />
    <Order Build="Traveler59PowerProjector" />
    <Order Build="Traveler59StatisChamber" />
    <Order Build="Traveler59Reactor" />

    <Order Build="Traveler59StalkerSquad" />
    <Order Build="Traveler59StalkerSquad" />
    <Order Build="Traveler59StalkerSquad" />
    <Order Build="Traveler59StalkerSquad" />
    <Order Build="Traveler59StalkerSquad" />
    <Order Build="Traveler59StalkerSquad" />
    <Order Build="Traveler59StalkerSquad" />
    <Order Build="Traveler59StalkerSquad" />
    <Order Build="Traveler59StalkerSquad" />
    <Order Build="Traveler59StalkerSquad" />
    <Order Time="175s" />
  </SkirmishOpeningMove>

  <SkirmishOpeningMove
   id="Traveler59MechapedeRush"
   Side="Traveler59">

    <Order Build="Traveler59TiberiumTower" />
    <Order Build="Traveler59PowerProjector" />
    <Order Build="Traveler59TiberiumTower" />
    <Order Build="Traveler59TiberiumTower" />
    <Order Build="Traveler59PowerProjector" />
    <Order Build="Traveler59ControlCenter" />
    <Order Build="Traveler59Reactor" />
    <Order Build="Traveler59Gateway" />
    <Order Build="Traveler59PowerProjector" />
    <Order Build="Traveler59Gateway" />

    <Order Build="Traveler59CustomizableVehicle" />
    <Order Build="Traveler59CustomizableVehicle" />
    <Order Build="Traveler59CustomizableVehicle" />
    <Order Build="Traveler59CustomizableVehicle" />
    <Order Build="Traveler59CustomizableVehicle" />
    <Order Build="Traveler59CustomizableVehicle" />
    <Order Time="175s" />

  </SkirmishOpeningMove>
</AssetDeclaration>