<?xml version="1.0" encoding="utf-8"?>
<AssetDeclaration xmlns="uri:ea.com:eala:asset" xmlns:xsi="http://www.w3.org/2001/XMLSchema-instance">
	<Tags></Tags>
	<Includes>
		<Include
			type="all"
			source="ART:CBIrrigation01.w3x" />
	</Includes>
	<GameObject
		id="CBIrrigation01"
		SelectPortrait="SABarracks_L"
		ButtonImage="SABarracks"
		Side="Civilian"
		EditorSorting="MISC_MAN_MADE"
		TransportSlotCount="1"
		BuildCost="1"
		BuildTime="10.0"
		CommandSet="EmptyCommandSet"
		KindOf="STRUCTURE SELECTABLE IMMOBILE CAN_CAST_REFLECTIONS CLEARED_BY_BUILD"
		RadarPriority="STRUCTURE"
		EditorName="CBIrrigation01"
		Browser="REGION WASHINGTON_DC_DC MISC_MAN_MADE">
		<DisplayName>CBIrrigation01</DisplayName>
		<ArmorSet
			Armor="NoArmor" />
		<Draws>
			<ScriptedModelDraw
				id="ModuleTag_Draw"
				OkToChangeModelColor="true">
				<ModelConditionState
					ParseCondStateType="PARSE_DEFAULT">
					<Model
						Name="CBIrrigation01" />
				</ModelConditionState>
			</ScriptedModelDraw>
		</Draws>
		<Behaviors></Behaviors>
		<Body>
			<ActiveBody
				id="ModuleTag_Body"
				MaxHealth="3000.0"
				InitialHealth="3000.0" />
		</Body>
		<Geometry
			IsSmall="false">
			<Shape
				Type="CYLINDER"
				MajorRadius="5.0"
				Height="100.0"></Shape>
		</Geometry>
		<ShadowInfo
			Type="VOLUME" />
		<VisionInfo
			VisionRange="100"
			ShroudClearingRange="200" />
	</GameObject>
</AssetDeclaration>